dbmanagr/__init__.py
dbmanagr/args.py
dbmanagr/comment.py
dbmanagr/config.py
dbmanagr/daemon.py
dbmanagr/exception.py
dbmanagr/formatter.py
dbmanagr/jsonable.py
dbmanagr/logger.py
dbmanagr/options.py
dbmanagr/querybuilder.py
dbmanagr/queryfilter.py
dbmanagr/version.py
dbmanagr/wrapper.py
dbmanagr/writer.py
dbmanagr/command/__init__.py
dbmanagr/command/activity/__init__.py
dbmanagr/command/activity/args.py
dbmanagr/command/activity/writer.py
dbmanagr/command/argumentor/__init__.py
dbmanagr/command/argumentor/args.py
dbmanagr/command/argumentor/writer.py
dbmanagr/command/daemon/__init__.py
dbmanagr/command/daemon/args.py
dbmanagr/command/differ/__init__.py
dbmanagr/command/differ/args.py
dbmanagr/command/differ/writer.py
dbmanagr/command/executer/__init__.py
dbmanagr/command/executer/args.py
dbmanagr/command/executer/writer.py
dbmanagr/command/exporter/__init__.py
dbmanagr/command/exporter/args.py
dbmanagr/command/exporter/writer.py
dbmanagr/command/grapher/__init__.py
dbmanagr/command/grapher/args.py
dbmanagr/command/grapher/node.py
dbmanagr/command/grapher/writer.py
dbmanagr/command/navigator/__init__.py
dbmanagr/command/navigator/args.py
dbmanagr/command/navigator/dto.py
dbmanagr/command/navigator/writer.py
dbmanagr/driver/__init__.py
dbmanagr/driver/mysql/__init__.py
dbmanagr/driver/mysql/databaseconnection.py
dbmanagr/driver/mysql/driver.py
dbmanagr/driver/postgresql/__init__.py
dbmanagr/driver/postgresql/databaseconnection.py
dbmanagr/driver/postgresql/driver.py
dbmanagr/driver/postgresql/version/__init__.py
dbmanagr/driver/postgresql/version/v91.py
dbmanagr/driver/postgresql/version/v92.py
dbmanagr/driver/sqlite/__init__.py
dbmanagr/driver/sqlite/databaseconnection.py
dbmanagr/driver/sqlite/driver.py
dbmanagr/dto/__init__.py
dbmanagr/dto/column.py
dbmanagr/dto/foreignkey.py
dbmanagr/dto/mapper.py
dbmanagr/dto/node.py
dbmanagr/dto/row.py
dbmanagr/dto/table.py
dbmanagr/model/__init__.py
dbmanagr-0.28.3.dist-info/DESCRIPTION.rst
dbmanagr-0.28.3.dist-info/entry_points.txt
dbmanagr-0.28.3.dist-info/METADATA
dbmanagr-0.28.3.dist-info/metadata.json
dbmanagr-0.28.3.dist-info/RECORD
dbmanagr-0.28.3.dist-info/top_level.txt
dbmanagr-0.28.3.dist-info/WHEEL
