Metadata-Version: 2.0
Name: dbmanagr
Version: 0.28.3
Summary: The database manager for the command line
Home-page: https://github.com/resamsel/dbmanagr
Author: René Samselnig
Author-email: me@resamsel.com
License: GPLv3+
Keywords: database navigator exporter grapher postgres sqlite graphviz diff
Platform: UNKNOWN
Classifier: Development Status :: 4 - Beta
Classifier: Intended Audience :: Developers
Classifier: Intended Audience :: Information Technology
Classifier: Intended Audience :: System Administrators
Classifier: License :: OSI Approved :: GNU General Public License v3 or later (GPLv3+)
Classifier: Natural Language :: English
Classifier: Operating System :: OS Independent
Classifier: Programming Language :: Python :: 2
Classifier: Programming Language :: Python :: 2.7
Classifier: Programming Language :: Python :: 2 :: Only
Classifier: Topic :: Database
Classifier: Topic :: Database :: Front-Ends
Classifier: Topic :: System :: Systems Administration
Classifier: Topic :: Utilities
Requires-Dist: sqlalchemy (==0.9.10)
Requires-Dist: sqlparse (>=0.1.13)
Requires-Dist: ijson (>=2.0)
Requires-Dist: pyyaml (>=3.11)
